gym_duckietown/__init__.py
gym_duckietown/collision.py
gym_duckietown/config.py
gym_duckietown/distortion.py
gym_duckietown/generate_topdown_png.py
gym_duckietown/graphics.py
gym_duckietown/launcher.py
gym_duckietown/objects.py
gym_duckietown/objmesh.py
gym_duckietown/requirements.txt
gym_duckietown/simulator.py
gym_duckietown/utils.py
gym_duckietown/wrappers.py
gym_duckietown/__pycache__/__init__.cpython-36.pyc
gym_duckietown/__pycache__/collision.cpython-36.pyc
gym_duckietown/__pycache__/graphics.cpython-36.pyc
gym_duckietown/__pycache__/objects.cpython-36.pyc
gym_duckietown/__pycache__/objmesh.cpython-36.pyc
gym_duckietown/__pycache__/simulator.cpython-36.pyc
gym_duckietown/__pycache__/utils.cpython-36.pyc
gym_duckietown/__pycache__/wrappers.cpython-36.pyc
gym_duckietown/envs/__init__.py
gym_duckietown/envs/duckiebot_env.py
gym_duckietown/envs/duckietown_env.py
gym_duckietown/envs/multimap_env.py
gym_duckietown/envs/__pycache__/__init__.cpython-36.pyc
gym_duckietown/envs/__pycache__/duckiebot_env.cpython-36.pyc
gym_duckietown/envs/__pycache__/duckietown_env.cpython-36.pyc
gym_duckietown/envs/__pycache__/multimap_env.cpython-36.pyc
gym_duckietown/maps/4way.yaml
gym_duckietown/maps/calibration_map.yaml
gym_duckietown/maps/loop_dyn_duckiebots.yaml
gym_duckietown/maps/loop_empty.yaml
gym_duckietown/maps/loop_obstacles.yaml
gym_duckietown/maps/loop_pedestrians.yaml
gym_duckietown/maps/regress_4way_adam.yaml
gym_duckietown/maps/regress_4way_drivable.yaml
gym_duckietown/maps/small_loop.yaml
gym_duckietown/maps/small_loop_cw.yaml
gym_duckietown/maps/straight_road.yaml
gym_duckietown/maps/udem1.yaml
gym_duckietown/maps/zigzag_dists.yaml
gym_duckietown/meshes/barrier.obj
gym_duckietown/meshes/building.obj
gym_duckietown/meshes/bus.obj
gym_duckietown/meshes/cone.obj
gym_duckietown/meshes/duckie.obj
gym_duckietown/meshes/duckiebot.mtl
gym_duckietown/meshes/duckiebot.obj
gym_duckietown/meshes/house.obj
gym_duckietown/meshes/sign_4_way_intersect.mtl
gb_duckietown_gym_daffy-5.0.15.dist-info/LICENSE.pdf
gb_duckietown_gym_daffy-5.0.15.dist-info/METADATA
gb_duckietown_gym_daffy-5.0.15.dist-info/WHEEL
gb_duckietown_gym_daffy-5.0.15.dist-info/entry_points.txt
gb_duckietown_gym_daffy-5.0.15.dist-info/top_level.txt
gb_duckietown_gym_daffy-5.0.15.dist-info/RECORD
