Metadata-Version: 2.1
Name: gb-duckietown-gym-daffy
Version: 5.0.15
Summary: UNKNOWN
Home-page: UNKNOWN
Author: UNKNOWN
Author-email: UNKNOWN
License: UNKNOWN
Keywords: duckietown,environment,agent,rl,openaigym,openai-gym,gym
Platform: UNKNOWN
Requires-Dist: gym (>=0.9.0)
Requires-Dist: numpy (>=1.10.0)
Requires-Dist: pyglet (<=1.3.2,>=1.2.0)
Requires-Dist: pyzmq (>=16.0.0)
Requires-Dist: scikit-image (>=0.13.1)
Requires-Dist: opencv-python (>=3.4)
Requires-Dist: pyyaml (>=3.11)
Requires-Dist: cloudpickle
Requires-Dist: duckietown-world-daffy
Requires-Dist: pygeometry
Requires-Dist: dataclasses
Requires-Dist: carnivalmirror (==0.6.2)
